dl_plus/extractors/un1def/goodgame.py
dl_plus_extractor_un1def_goodgame-0.2.1.dist-info/LICENSE
dl_plus_extractor_un1def_goodgame-0.2.1.dist-info/METADATA
dl_plus_extractor_un1def_goodgame-0.2.1.dist-info/WHEEL
dl_plus_extractor_un1def_goodgame-0.2.1.dist-info/top_level.txt
dl_plus_extractor_un1def_goodgame-0.2.1.dist-info/RECORD
