Metadata-Version: 2.1
Name: dl-plus-extractor-un1def-goodgame
Version: 0.2.1
Summary: A dl-plus extractor plugin for GoodGame streaming platform
Author-email: Dmitry Meyer <me@undef.im>
License: MIT
Project-URL: Homepage, https://github.com/un-def/dl-plus-extractor-un1def-goodgame
Project-URL: Repository, https://github.com/un-def/dl-plus-extractor-un1def-goodgame.git
Project-URL: Changelog, https://github.com/un-def/dl-plus-extractor-un1def-goodgame/releases
Project-URL: Issues, https://github.com/un-def/dl-plus-extractor-un1def-goodgame/issues
Requires-Python: >=3.8
License-File: LICENSE
Provides-Extra: dl-plus
Requires-Dist: dl-plus >=0.6.0 ; extra == 'dl-plus'
